{"Loading.atlas":["masetr/RYFrameWork/bin/Loading/",["R.png","W.png","Y.png","loading上条.png","任.png","加载顿号.png","底部背景色块.png","游.png","玩.png","资源加载中.png"]],"res/atlas/ClickGetPrize.atlas":["ClickGetPrize/",["NewProject.png","dianjianniu.png","gongxihuodeMark.png","henyihan.png","jiantou.png","jindutiao.png","jindutiao1.png","juxing568.png","meiriqiandaolansebg.png","quanji.png","queding.png","zi.png"]],"res/atlas/GameUI.atlas":["GameUI/",["3D旋转预览皮肤.png","Blue_Light.png","Hand.png","不用了.png","左右滑动出发.png","恭喜获得最新皮肤.png","矩形 619.png","立即使用.png","竞赛模式.png","箭头.png"]],"res/atlas/KRQ.atlas":["KRQ/",["bg1.png","cebianlan1.png","daochuyead.png","fanhui.png","jieduanad.png","jiesuanyead.png","jixuyouxi.png","mark.png","shouyead.png","tuichu.png","tuijian.png","xiaochengxu.png","xiaochengxubg.png","yuan.png","zuijinshiyong.png"]],"res/atlas/Loading.atlas":["Loading/",["loadingbg.png","轮胎压压乐logo.png"]],"res/atlas/Template.atlas":["Template/",["1.0.0.png","baoxiangjiangli.png","di.png","fangqi.png","fanhuianniu.png","fanhuishouye.png","gongsilogo.png","guan.png","guanbiX.png","guanqiashuzi.png","jiesuanjiemiandaochukuang.png","jinbi.png","jinbidikuang.png","jinbishuzi.png","jindutiaodiceng.png","jindutiaoshangceng.png","jixuyouxi.png","jixuyouxikaobei.png","juxing619.png","kuangdiangtips.png","lALPDhmOqQn5E2DMj8y8_188_143.png","lALPDiQ3JPhHV9hsaA_104_108.png","lALPDiQ3JPhHY6dsaA_104_108.png","lunboguanggaowei.png","quedinganniu.png","sambeilingqu.png","xiayiguan.png","xiayiguananniu.png","xunituichujian.png","zaicitiaozhan.png","zaicitiaozhananniu.png"]]}